sox/__init__.py
sox/combine.py
sox/core.py
sox/file_info.py
sox/log.py
sox/transform.py
sox/utilities.py
sox/version.py
sox-1.4.1.dist-info/LICENSE
sox-1.4.1.dist-info/METADATA
sox-1.4.1.dist-info/WHEEL
sox-1.4.1.dist-info/pbr.json
sox-1.4.1.dist-info/top_level.txt
sox-1.4.1.dist-info/RECORD
