Metadata-Version: 2.1
Name: sox
Version: 1.4.1
Summary: Python wrapper around SoX.
Home-page: https://github.com/rabitt/pysox
Author: Rachel Bittner
Author-email: rachel.bittner@nyu.edu
License: BSD-3-Clause
Download-URL: http://github.com/rabitt/pysox/releases
Keywords: audio effects SoX
Platform: UNKNOWN
Provides-Extra: tests
Provides-Extra: docs
